truequery.py
truequery_api-1.0.0.dist-info/METADATA
truequery_api-1.0.0.dist-info/WHEEL
truequery_api-1.0.0.dist-info/entry_points.txt
truequery_api-1.0.0.dist-info/top_level.txt
truequery_api-1.0.0.dist-info/RECORD
